chat.py
chat_node.py
config.py
debouncer.py
events.py
format.py
llm.py
llm_registry.py
log.py
main.py
mapper.py
mods.py
selection.py
state.py
custom_modules/3t.py
custom_modules/ambi.py
custom_modules/cea.py
custom_modules/cex.py
custom_modules/clarity.py
custom_modules/crystal.py
custom_modules/cssv.py
custom_modules/discussurl.py
custom_modules/example.py
custom_modules/fml.py
custom_modules/gact.py
custom_modules/grug.py
custom_modules/l33t.py
custom_modules/meow.py
custom_modules/ow.py
custom_modules/pad.py
custom_modules/pdsv.py
custom_modules/polyglot.py
custom_modules/recpl.py
custom_modules/stcl.py
custom_modules/tmsv.py
custom_modules/tri.py
custom_modules/unstable.py
custom_modules/usv.py
custom_modules/webui_artifact.py
custom_modules/wswp.py
middleware/request_id.py
middleware/request_state.py
modules/autotemp.py
modules/concept.py
modules/dnd.py
modules/dot.py
modules/eli5.py
modules/g1.py
modules/klmbr.py
modules/markov.py
modules/mcts.py
modules/nbs.py
modules/ponder.py
modules/promx.py
modules/r0.py
modules/rcn.py
modules/supersummer.py
tools/registry.py
harbor_boost-0.3.19.dist-info/METADATA
harbor_boost-0.3.19.dist-info/WHEEL
harbor_boost-0.3.19.dist-info/top_level.txt
harbor_boost-0.3.19.dist-info/RECORD
