Metadata-Version: 2.4
Name: harbor-boost
Version: 0.3.19
Summary: Optimising LLM proxy
Requires-Python: >=3.12
Requires-Dist: fastapi==0.111.0
Requires-Dist: uvicorn[standard]==0.30.6
Requires-Dist: requests==2.32.3
Requires-Dist: aiohttp==3.10.5
Requires-Dist: litellm==1.65.7
Requires-Dist: mcp==1.6.0
Requires-Dist: cachetools==5.5.2
Requires-Dist: asyncache==0.3.1
Requires-Dist: openai
Requires-Dist: websockets==15.0.1
